[{"time":"22 Apr 2019, 8:23:57 pm","prod_name":"Мышка","action":"add"},{"time":"22 Apr 2019, 8:24:05 pm","prod_name":"Ноутбук","action":"change"},{"time":"22 Apr 2019, 8:24:18 pm","prod_name":"Мышка","action":"remove"},{"time":"03 Jun 2019, 6:28:50 pm","prod_name":"Gamepad","action":"add"},{"time":"03 Jun 2019, 6:28:51 pm","prod_name":"Laptop","action":"change"},{"time":"03 Jun 2019, 6:28:53 pm","prod_name":"Laptop","action":"change"},{"time":"03 Jun 2019, 6:28:53 pm","prod_name":"Laptop","action":"change"},{"time":"03 Jun 2019, 6:28:53 pm","prod_name":"Laptop","action":"change"},{"time":"03 Jun 2019, 6:28:53 pm","prod_name":"Laptop","action":"change"},{"time":"03 Jun 2019, 6:28:53 pm","prod_name":"Laptop","action":"change"},{"time":"03 Jun 2019, 6:28:54 pm","prod_name":"Laptop","action":"change"},{"time":"03 Jun 2019, 6:28:54 pm","prod_name":"Laptop","action":"change"},{"time":"03 Jun 2019, 6:28:54 pm","prod_name":"Laptop","action":"change"},{"time":"03 Jun 2019, 6:28:54 pm","prod_name":"Laptop","action":"change"},{"time":"03 Jun 2019, 6:28:54 pm","prod_name":"Laptop","action":"change"},{"time":"03 Jun 2019, 6:28:54 pm","prod_name":"Laptop","action":"change"},{"time":"03 Jun 2019, 6:28:54 pm","prod_name":"Laptop","action":"change"},{"time":"03 Jun 2019, 6:28:55 pm","prod_name":"Laptop","action":"change"},{"time":"03 Jun 2019, 6:28:55 pm","prod_name":"Laptop","action":"change"},{"time":"03 Jun 2019, 6:28:55 pm","prod_name":"Laptop","action":"change"},{"time":"03 Jun 2019, 6:28:55 pm","prod_name":"Laptop","action":"change"},{"time":"03 Jun 2019, 6:28:55 pm","prod_name":"Laptop","action":"remove"},{"time":"03 Jun 2019, 6:28:55 pm","prod_name":"Gamepad","action":"remove"}]